TestNotification/__init__.py
robotframework_testnotify-1.0.0.dist-info/METADATA
robotframework_testnotify-1.0.0.dist-info/WHEEL
robotframework_testnotify-1.0.0.dist-info/top_level.txt
robotframework_testnotify-1.0.0.dist-info/RECORD
