Metadata-Version: 2.1
Name: robotframework-testnotify
Version: 1.0.0
Summary: Send notifications to chat using Robot Framework.
Home-page: https://github.com/barbosamp/robotframework-testnotification.git
Author: Marcos Barbosa
Author-email: 
License: MIT
Classifier: License :: OSI Approved :: MIT License
Classifier: Programming Language :: Python :: 3
Classifier: Programming Language :: Python :: 3.8
Classifier: Programming Language :: Python :: 3.9
Classifier: Programming Language :: Python :: 3.10
Classifier: Programming Language :: Python :: 3.11
Classifier: Programming Language :: Python :: 3.12
Requires-Dist: requests
